fps_auth_jupyterhub/__init__.py
fps_auth_jupyterhub/config.py
fps_auth_jupyterhub/db.py
fps_auth_jupyterhub/launch.py
fps_auth_jupyterhub/main.py
fps_auth_jupyterhub/models.py
fps_auth_jupyterhub/py.typed
fps_auth_jupyterhub/routes.py
fps_auth_jupyterhub-0.9.7.dist-info/licenses/COPYING.md
fps_auth_jupyterhub-0.9.7.dist-info/WHEEL
fps_auth_jupyterhub-0.9.7.dist-info/entry_points.txt
fps_auth_jupyterhub-0.9.7.dist-info/METADATA
fps_auth_jupyterhub-0.9.7.dist-info/RECORD
